MANIFEST.in
README.md
requirements.txt
setup.cfg
setup.py
tamagotchi_tandersen/__init__.py
tamagotchi_tandersen/__main__.py
tamagotchi_tandersen.egg-info/PKG-INFO
tamagotchi_tandersen.egg-info/SOURCES.txt
tamagotchi_tandersen.egg-info/dependency_links.txt
tamagotchi_tandersen.egg-info/requires.txt
tamagotchi_tandersen.egg-info/top_level.txt
tamagotchi_tandersen/abstract/__init__.py
tamagotchi_tandersen/abstract/actor.py
tamagotchi_tandersen/abstract/consumable.py
tamagotchi_tandersen/abstract/status_element.py
tamagotchi_tandersen/assets/cute-fox.png
tamagotchi_tandersen/assets/fox-middle.png
tamagotchi_tandersen/assets/fox-old.png
tamagotchi_tandersen/assets/fox-sleeping.png
tamagotchi_tandersen/assets/pixel-apple.jpg
tamagotchi_tandersen/assets/pixel-pear.png
tamagotchi_tandersen/assets/pixel-strawberry.jpg
tamagotchi_tandersen/classes/__init__.py
tamagotchi_tandersen/classes/coordinate.py
tamagotchi_tandersen/classes/food.py
tamagotchi_tandersen/classes/food_inventory.py
tamagotchi_tandersen/classes/game_board.py
tamagotchi_tandersen/classes/pet.py
tamagotchi_tandersen/classes/state_bars.py
tamagotchi_tandersen/enums/__init__.py
tamagotchi_tandersen/enums/actor_state.py
tamagotchi_tandersen/enums/age.py
tamagotchi_tandersen/enums/direction.py
tamagotchi_tandersen/factory/__init__.py
tamagotchi_tandersen/factory/consumable_factory.py
tamagotchi_tandersen/factory/status_bar_factory.py
venv/lib/python3.6/site-packages/pygame/examples/data/alien1.jpg
venv/lib/python3.6/site-packages/pygame/examples/data/alien1.png
venv/lib/python3.6/site-packages/pygame/examples/data/alien2.png
venv/lib/python3.6/site-packages/pygame/examples/data/alien3.png
venv/lib/python3.6/site-packages/pygame/examples/data/brick.png
venv/lib/python3.6/site-packages/pygame/examples/data/city.png
venv/lib/python3.6/site-packages/pygame/examples/data/midikeys.png
venv/lib/python3.6/site-packages/pygame/examples/data/static.png
venv/lib/python3.6/site-packages/pygame/tests/fixtures/fonts/A_PyGameMono-8.png
venv/lib/python3.6/site-packages/pygame/tests/fixtures/fonts/u13079_PyGameMono-8.png