Metadata-Version: 2.1
Name: tamagotchi-tandersen
Version: 1.0.0
Summary: My attempt at the Tamagotchi challenge
Home-page: https://github.com/Tristan-Andersen/Tamagotchi-challenge
Author: Tristan Andersen
License: UNKNOWN
Platform: UNKNOWN
Classifier: Programming Language :: Python :: 3
Classifier: License :: OSI Approved :: MIT License
Classifier: Operating System :: OS Independent
Requires-Python: >=3.6
